aguaclara/__init__.py
aguaclara/play.py
aguaclara/core/__init__.py
aguaclara/core/cache.py
aguaclara/core/constants.py
aguaclara/core/drills.py
aguaclara/core/head_loss.py
aguaclara/core/materials.py
aguaclara/core/onshape_parser.py
aguaclara/core/physchem.py
aguaclara/core/pipes.py
aguaclara/core/units.py
aguaclara/core/utility.py
aguaclara/core/data/pipe_database.csv
aguaclara/core/data/unit_definitions.txt
aguaclara/design/__init__.py
aguaclara/design/cdc.py
aguaclara/design/component.py
aguaclara/design/ent.py
aguaclara/design/ent_floc.py
aguaclara/design/filter.py
aguaclara/design/floc.py
aguaclara/design/human_access.py
aguaclara/design/lfom.py
aguaclara/design/pipeline.py
aguaclara/design/plant.py
aguaclara/design/sed.py
aguaclara/design/sed_chan.py
aguaclara/design/sed_tank.py
aguaclara/design/data/fitting_database.csv
aguaclara/design/data/pipe_database.csv
aguaclara/research/Reactor_data.txt
aguaclara/research/__init__.py
aguaclara/research/environmental_processes_analysis.py
aguaclara/research/floc_model.py
aguaclara/research/peristaltic_pump.py
aguaclara/research/procoda_parser.py
aguaclara/research/stock_qc.py
aguaclara/research/data/3_stop_tubing.txt
aguaclara/research/data/LS_tubing.txt
tests/__init__.py
tests/research/__init__.py
tests/research/test_EPA.py
tests/research/test_ProCoDA_Parser.py
tests/research/test_floc_model.py
tests/research/test_peristaltic_pump.py
tests/research/test_stock_qc.py
aguaclara-0.4.0.dist-info/LICENSE
aguaclara-0.4.0.dist-info/METADATA
aguaclara-0.4.0.dist-info/WHEEL
aguaclara-0.4.0.dist-info/top_level.txt
aguaclara-0.4.0.dist-info/RECORD
