Metadata-Version: 2.1
Name: aguaclara
Version: 0.4.0
Summary: An open-source Python package for designing and performing research on AguaClara water treatment plants.
Home-page: https://github.com/AguaClara-Reach/aguaclara
Author: AguaClara Reach
Author-email: mwebershirk@aguaclarareach.org
License: MIT
Project-URL: Documentation, https://aguaclara-reach.github.io/aguaclara/
Classifier: Programming Language :: Python :: 3.8
Classifier: Programming Language :: Python :: 3.9
Requires-Python: >=3.8
License-File: LICENSE
Requires-Dist: matplotlib
Requires-Dist: urllib3
Requires-Dist: pint
Requires-Dist: pandas
Requires-Dist: scipy
Requires-Dist: onshape-client
Requires-Dist: numpy
Provides-Extra: all
Requires-Dist: matplotlib; extra == "all"
Requires-Dist: urllib3; extra == "all"
Requires-Dist: pint; extra == "all"
Requires-Dist: pandas; extra == "all"
Requires-Dist: scipy; extra == "all"
Requires-Dist: onshape-client; extra == "all"
Requires-Dist: numpy; extra == "all"
Requires-Dist: black; extra == "all"
Requires-Dist: flake8; extra == "all"
Requires-Dist: codecov; extra == "all"
Requires-Dist: pytest; extra == "all"
Requires-Dist: pytest-cov; extra == "all"
Requires-Dist: pytest-html; extra == "all"
Requires-Dist: Sphinx; extra == "all"
Requires-Dist: sphinx-rtd-theme; extra == "all"
Requires-Dist: tox; extra == "all"
Requires-Dist: ipykernel; extra == "all"
Provides-Extra: dev
Requires-Dist: black; extra == "dev"
Requires-Dist: flake8; extra == "dev"
Requires-Dist: codecov; extra == "dev"
Requires-Dist: pytest; extra == "dev"
Requires-Dist: pytest-cov; extra == "dev"
Requires-Dist: pytest-html; extra == "dev"
Requires-Dist: Sphinx; extra == "dev"
Requires-Dist: sphinx-rtd-theme; extra == "dev"
Requires-Dist: tox; extra == "dev"
Requires-Dist: matplotlib; extra == "dev"
Requires-Dist: ipykernel; extra == "dev"
Provides-Extra: setup
Provides-Extra: test
Requires-Dist: black; extra == "test"
Requires-Dist: flake8; extra == "test"
Requires-Dist: codecov; extra == "test"
Requires-Dist: pytest; extra == "test"
Requires-Dist: pytest-cov; extra == "test"
Requires-Dist: pytest-html; extra == "test"
